darkfeed/__init__.py
darkfeed/main.py
darkfeed/darkfeed.egg-info/PKG-INFO
darkfeed/darkfeed.egg-info/SOURCES.txt
darkfeed/darkfeed.egg-info/dependency_links.txt
darkfeed/darkfeed.egg-info/entry_points.txt
darkfeed/darkfeed.egg-info/requires.txt
darkfeed/darkfeed.egg-info/top_level.txt
darkfeed/lib/dark.py
darkfeed/lib/keywords.py
darkfeed/lib/web_service.py
darkfeed/lib/__pycache__/dark.cpython-311.pyc
darkfeed/lib/static/css/dash_style.css
darkfeed/lib/static/css/index_style.css
darkfeed/lib/static/css/table_style.css
darkfeed/lib/static/js/table.js
darkfeed/lib/static/webfonts/chart.js
darkfeed/lib/static/webfonts/chart.min.js
darkfeed/lib/static/webfonts/d3.v7.min.js
darkfeed/lib/static/webfonts/dataTables.js
darkfeed/lib/static/webfonts/font-awesome.min.css
darkfeed/lib/static/webfonts/topojson.v3.min.js
darkfeed/lib/static/webfonts/world-110m.v1.json
darkfeed/lib/static/webfonts/world-110m.v1.tsv
darkfeed/lib/static/webfonts/xlsx.full.min.js
darkfeed/lib/templates/cti_news.html
darkfeed/lib/templates/dashboard.html
darkfeed/lib/templates/index.html
darkfeed/lib/templates/ransomwares.html
darkfeed-1.5.dist-info/METADATA
darkfeed-1.5.dist-info/WHEEL
darkfeed-1.5.dist-info/entry_points.txt
darkfeed-1.5.dist-info/top_level.txt
darkfeed-1.5.dist-info/RECORD
