Metadata-Version: 2.1
Name: darkfeed
Version: 1.5
Summary: A CLI and GUI parser for data from Dark Feed
Home-page: https://github.com/santiag02/DarkFeed
Author: Camila Santiago
Keywords: ransomware,victims,darkfeed,dark feed
Requires-Dist: python-dateutil
Requires-Dist: requests
Requires-Dist: openpyxl
Requires-Dist: Flask
